autochat/__init__.py
autochat/base.py
autochat/chat.py
autochat/mcp.py
autochat/model.py
autochat/utils.py
autochat/providers/anthropic.py
autochat/providers/base_provider.py
autochat/providers/default.py
autochat/providers/openai.py
autochat/providers/openai_function_legacy.py
autochat/providers/openai_function_shim.py
autochat/providers/utils.py
autochat-0.19.0.dist-info/licenses/LICENSE
autochat-0.19.0.dist-info/METADATA
autochat-0.19.0.dist-info/WHEEL
autochat-0.19.0.dist-info/top_level.txt
autochat-0.19.0.dist-info/RECORD
